ganx/MAXRF_class.py
ganx/RGB_segmentation_utils.py
ganx/XRF_generator_classes.py
ganx/__init__.py
ganx/generator_methods.py
ganx-0.0.2.dist-info/LICENSE
ganx-0.0.2.dist-info/METADATA
ganx-0.0.2.dist-info/WHEEL
ganx-0.0.2.dist-info/top_level.txt
ganx-0.0.2.dist-info/RECORD
