Metadata-Version: 2.1
Name: ganx
Version: 0.0.2
Author: Alessandro Bombini
License: Apache License 2.0
Project-URL: Homepage, https://github.com/androbomb/ganX.git
Keywords: MA-XRF
Classifier: License :: OSI Approved :: Apache Software License
Classifier: Programming Language :: Python
Classifier: Programming Language :: Python :: 3
Classifier: Intended Audience :: Science/Research
Classifier: Topic :: Scientific/Engineering :: Physics
Classifier: Topic :: Scientific/Engineering :: Image Processing
Classifier: Development Status :: 2 - Pre-Alpha
Requires-Python: >=3.6
License-File: LICENSE
Requires-Dist: h5py
Requires-Dist: Pillow
Requires-Dist: matplotlib
Requires-Dist: numpy
Requires-Dist: scikit-image
Requires-Dist: scikit-learn
Requires-Dist: scipy
